pyreflexion/__init__.py
pyreflexion-0.0.1.dev0.dist-info/METADATA
pyreflexion-0.0.1.dev0.dist-info/WHEEL
pyreflexion-0.0.1.dev0.dist-info/top_level.txt
pyreflexion-0.0.1.dev0.dist-info/RECORD
