Metadata-Version: 2.1
Name: pyreflexion
Version: 0.0.1.dev0
Summary: pyreflexion - Reflexion: an autonomous agent with dynamic memory and self-reflection
Author: Shadow Walker
License: UNKNOWN
Keywords: pyreflexion
Platform: UNKNOWN
Classifier: Programming Language :: Python :: 3
Classifier: Programming Language :: Python :: 3.8
Classifier: Programming Language :: Python :: 3.9
Classifier: Programming Language :: Python :: 3.10
Requires-Dist: torch
